aws_sms_service/__init__.py
aws_sms_service/example.py
aws_sms_service-0.0.7.dist-info/LICENSE
aws_sms_service-0.0.7.dist-info/METADATA
aws_sms_service-0.0.7.dist-info/WHEEL
aws_sms_service-0.0.7.dist-info/top_level.txt
aws_sms_service-0.0.7.dist-info/RECORD
