Metadata-Version: 2.1
Name: aws-sms-service
Version: 0.0.7
Summary: aws_sms_service
Home-page: https://github.com/Quakingaspen-codehub/aws_sms_service
Author: QuakingAspen
Author-email: info@quakingaspen.net
License: UNKNOWN
Platform: UNKNOWN
Classifier: Programming Language :: Python :: 3
Classifier: License :: OSI Approved :: MIT License
Classifier: Operating System :: OS Independent
Requires-Python: >=3.6
